with_.py
with_as_a_function-1.1.0.dist-info/LICENSE
with_as_a_function-1.1.0.dist-info/METADATA
with_as_a_function-1.1.0.dist-info/WHEEL
with_as_a_function-1.1.0.dist-info/top_level.txt
with_as_a_function-1.1.0.dist-info/RECORD
