Metadata-Version: 1.1
Name: with-as-a-function
Version: 1.1.0
Summary: Use context managers with a function instead of a statement.
Home-page: https://github.com/mentalisttraceur/python-with
Author: Alexander Kozhevnikov
Author-email: mentalisttraceur@gmail.com
License: 0BSD
Platform: UNKNOWN
Classifier: Development Status :: 6 - Mature
Classifier: Programming Language :: Python :: 3
Classifier: Programming Language :: Python :: 2
Classifier: Operating System :: OS Independent
